<?xml version="1.0" encoding="UTF-8"?>
<!DOCTYPE why3session PUBLIC "-//Why3//proof session v5//EN"
"http://why3.lri.fr/why3session.dtd">
<why3session shape_version="4">
<prover id="0" name="CVC4" version="1.4" timelimit="5" steplimit="0" memlimit="2000"/>
<prover id="1" name="Alt-Ergo" version="1.30" timelimit="5" steplimit="0" memlimit="2000"/>
<file name="../strsep.mlw" expanded="true">
<theory name="Function_strsep_safety" sum="b4c81a6c2f452f8de7d68bf5c7223193" expanded="true">
 <goal name="WP_parameter strsep" expl="Function strsep, safety" expanded="true">
 <proof prover="0"><result status="valid" time="0.64"/></proof>
 </goal>
</theory>
<theory name="Function_strsep_behaviors" sum="1e7bf0c182e1ca3f06d023ce00bf19d7" expanded="true">
 <goal name="WP_parameter strsep_ensures_default" expl="Function strsep, default behavior" expanded="true">
 <proof prover="1"><result status="valid" time="0.02" steps="37"/></proof>
 </goal>
 <goal name="WP_parameter strsep_ensures_input_null" expl="Function strsep, behavior input_null" expanded="true">
 <proof prover="1"><result status="valid" time="0.04" steps="20"/></proof>
 </goal>
 <goal name="WP_parameter strsep_ensures_input_strpbrk_not_null" expl="Function strsep, behavior input_strpbrk_not_null" expanded="true">
 <proof prover="0"><result status="valid" time="1.23"/></proof>
 </goal>
 <goal name="WP_parameter strsep_ensures_input_strpbrk_null" expl="Function strsep, behavior input_strpbrk_null" expanded="true">
 <proof prover="1"><result status="valid" time="0.09" steps="146"/></proof>
 </goal>
</theory>
<theory name="Axiomatic_Padding" sum="d41d8cd98f00b204e9800998ecf8427e" expanded="true">
</theory>
<theory name="Int32_of_Int16" sum="d41d8cd98f00b204e9800998ecf8427e" expanded="true">
</theory>
<theory name="Bit_int32_of_Bit_int16" sum="d41d8cd98f00b204e9800998ecf8427e" expanded="true">
</theory>
<theory name="Int64_of_Int16" sum="d41d8cd98f00b204e9800998ecf8427e" expanded="true">
</theory>
<theory name="Bit_int64_of_Bit_int16" sum="d41d8cd98f00b204e9800998ecf8427e" expanded="true">
</theory>
<theory name="Int64_of_Int32" sum="d41d8cd98f00b204e9800998ecf8427e" expanded="true">
</theory>
<theory name="Bit_int64_of_Bit_int32" sum="d41d8cd98f00b204e9800998ecf8427e" expanded="true">
</theory>
<theory name="Int8_of_Int16" sum="d41d8cd98f00b204e9800998ecf8427e" expanded="true">
</theory>
<theory name="Bit_int8_of_Bit_int16" sum="d41d8cd98f00b204e9800998ecf8427e" expanded="true">
</theory>
<theory name="Int8_of_Int32" sum="d41d8cd98f00b204e9800998ecf8427e" expanded="true">
</theory>
<theory name="Bit_int8_of_Bit_int32" sum="d41d8cd98f00b204e9800998ecf8427e" expanded="true">
</theory>
<theory name="Int8_of_Int64" sum="d41d8cd98f00b204e9800998ecf8427e" expanded="true">
</theory>
<theory name="Bit_int8_of_Bit_int64" sum="d41d8cd98f00b204e9800998ecf8427e" expanded="true">
</theory>
<theory name="Uint16_of_Int16" sum="d41d8cd98f00b204e9800998ecf8427e" expanded="true">
</theory>
<theory name="Bit_uint16_of_Bit_int16" sum="d41d8cd98f00b204e9800998ecf8427e" expanded="true">
</theory>
<theory name="Uint16_of_Int32" sum="d41d8cd98f00b204e9800998ecf8427e" expanded="true">
</theory>
<theory name="Bit_uint16_of_Bit_int32" sum="d41d8cd98f00b204e9800998ecf8427e" expanded="true">
</theory>
<theory name="Uint16_of_Int64" sum="d41d8cd98f00b204e9800998ecf8427e" expanded="true">
</theory>
<theory name="Bit_uint16_of_Bit_int64" sum="d41d8cd98f00b204e9800998ecf8427e" expanded="true">
</theory>
<theory name="Uint16_of_Int8" sum="d41d8cd98f00b204e9800998ecf8427e" expanded="true">
</theory>
<theory name="Bit_uint16_of_Bit_int8" sum="d41d8cd98f00b204e9800998ecf8427e" expanded="true">
</theory>
<theory name="Uint32_of_Int16" sum="d41d8cd98f00b204e9800998ecf8427e" expanded="true">
</theory>
<theory name="Bit_uint32_of_Bit_int16" sum="d41d8cd98f00b204e9800998ecf8427e" expanded="true">
</theory>
<theory name="Uint32_of_Int32" sum="d41d8cd98f00b204e9800998ecf8427e" expanded="true">
</theory>
<theory name="Bit_uint32_of_Bit_int32" sum="d41d8cd98f00b204e9800998ecf8427e" expanded="true">
</theory>
<theory name="Uint32_of_Int64" sum="d41d8cd98f00b204e9800998ecf8427e" expanded="true">
</theory>
<theory name="Bit_uint32_of_Bit_int64" sum="d41d8cd98f00b204e9800998ecf8427e" expanded="true">
</theory>
<theory name="Uint32_of_Int8" sum="d41d8cd98f00b204e9800998ecf8427e" expanded="true">
</theory>
<theory name="Bit_uint32_of_Bit_int8" sum="d41d8cd98f00b204e9800998ecf8427e" expanded="true">
</theory>
<theory name="Uint32_of_Uint16" sum="d41d8cd98f00b204e9800998ecf8427e" expanded="true">
</theory>
<theory name="Bit_uint32_of_Bit_uint16" sum="d41d8cd98f00b204e9800998ecf8427e" expanded="true">
</theory>
<theory name="Uint64_of_Int16" sum="d41d8cd98f00b204e9800998ecf8427e" expanded="true">
</theory>
<theory name="Bit_uint64_of_Bit_int16" sum="d41d8cd98f00b204e9800998ecf8427e" expanded="true">
</theory>
<theory name="Uint64_of_Int32" sum="d41d8cd98f00b204e9800998ecf8427e" expanded="true">
</theory>
<theory name="Bit_uint64_of_Bit_int32" sum="d41d8cd98f00b204e9800998ecf8427e" expanded="true">
</theory>
<theory name="Uint64_of_Int64" sum="d41d8cd98f00b204e9800998ecf8427e" expanded="true">
</theory>
<theory name="Bit_uint64_of_Bit_int64" sum="d41d8cd98f00b204e9800998ecf8427e" expanded="true">
</theory>
<theory name="Uint64_of_Int8" sum="d41d8cd98f00b204e9800998ecf8427e" expanded="true">
</theory>
<theory name="Bit_uint64_of_Bit_int8" sum="d41d8cd98f00b204e9800998ecf8427e" expanded="true">
</theory>
<theory name="Uint64_of_Uint16" sum="d41d8cd98f00b204e9800998ecf8427e" expanded="true">
</theory>
<theory name="Bit_uint64_of_Bit_uint16" sum="d41d8cd98f00b204e9800998ecf8427e" expanded="true">
</theory>
<theory name="Uint64_of_Uint32" sum="d41d8cd98f00b204e9800998ecf8427e" expanded="true">
</theory>
<theory name="Bit_uint64_of_Bit_uint32" sum="d41d8cd98f00b204e9800998ecf8427e" expanded="true">
</theory>
<theory name="Uint8_of_Int16" sum="d41d8cd98f00b204e9800998ecf8427e" expanded="true">
</theory>
<theory name="Bit_uint8_of_Bit_int16" sum="d41d8cd98f00b204e9800998ecf8427e" expanded="true">
</theory>
<theory name="Uint8_of_Int32" sum="d41d8cd98f00b204e9800998ecf8427e" expanded="true">
</theory>
<theory name="Bit_uint8_of_Bit_int32" sum="d41d8cd98f00b204e9800998ecf8427e" expanded="true">
</theory>
<theory name="Uint8_of_Int64" sum="d41d8cd98f00b204e9800998ecf8427e" expanded="true">
</theory>
<theory name="Bit_uint8_of_Bit_int64" sum="d41d8cd98f00b204e9800998ecf8427e" expanded="true">
</theory>
<theory name="Uint8_of_Int8" sum="d41d8cd98f00b204e9800998ecf8427e" expanded="true">
</theory>
<theory name="Bit_uint8_of_Bit_int8" sum="d41d8cd98f00b204e9800998ecf8427e" expanded="true">
</theory>
<theory name="Uint8_of_Uint16" sum="d41d8cd98f00b204e9800998ecf8427e" expanded="true">
</theory>
<theory name="Bit_uint8_of_Bit_uint16" sum="d41d8cd98f00b204e9800998ecf8427e" expanded="true">
</theory>
<theory name="Uint8_of_Uint32" sum="d41d8cd98f00b204e9800998ecf8427e" expanded="true">
</theory>
<theory name="Bit_uint8_of_Bit_uint32" sum="d41d8cd98f00b204e9800998ecf8427e" expanded="true">
</theory>
<theory name="Uint8_of_Uint64" sum="d41d8cd98f00b204e9800998ecf8427e" expanded="true">
</theory>
<theory name="Bit_uint8_of_Bit_uint64" sum="d41d8cd98f00b204e9800998ecf8427e" expanded="true">
</theory>
<theory name="Int16_of_Int32" sum="d41d8cd98f00b204e9800998ecf8427e" expanded="true">
</theory>
<theory name="Bit_int16_of_Bit_int32" sum="d41d8cd98f00b204e9800998ecf8427e" expanded="true">
</theory>
<theory name="Int16_of_Int64" sum="d41d8cd98f00b204e9800998ecf8427e" expanded="true">
</theory>
<theory name="Bit_int16_of_Bit_int64" sum="d41d8cd98f00b204e9800998ecf8427e" expanded="true">
</theory>
<theory name="Int32_of_Int64" sum="d41d8cd98f00b204e9800998ecf8427e" expanded="true">
</theory>
<theory name="Bit_int32_of_Bit_int64" sum="d41d8cd98f00b204e9800998ecf8427e" expanded="true">
</theory>
<theory name="Int16_of_Int8" sum="d41d8cd98f00b204e9800998ecf8427e" expanded="true">
</theory>
<theory name="Bit_int16_of_Bit_int8" sum="d41d8cd98f00b204e9800998ecf8427e" expanded="true">
</theory>
<theory name="Int32_of_Int8" sum="d41d8cd98f00b204e9800998ecf8427e" expanded="true">
</theory>
<theory name="Bit_int32_of_Bit_int8" sum="d41d8cd98f00b204e9800998ecf8427e" expanded="true">
</theory>
<theory name="Int64_of_Int8" sum="d41d8cd98f00b204e9800998ecf8427e" expanded="true">
</theory>
<theory name="Bit_int64_of_Bit_int8" sum="d41d8cd98f00b204e9800998ecf8427e" expanded="true">
</theory>
<theory name="Int16_of_Uint16" sum="d41d8cd98f00b204e9800998ecf8427e" expanded="true">
</theory>
<theory name="Bit_int16_of_Bit_uint16" sum="d41d8cd98f00b204e9800998ecf8427e" expanded="true">
</theory>
<theory name="Int32_of_Uint16" sum="d41d8cd98f00b204e9800998ecf8427e" expanded="true">
</theory>
<theory name="Bit_int32_of_Bit_uint16" sum="d41d8cd98f00b204e9800998ecf8427e" expanded="true">
</theory>
<theory name="Int64_of_Uint16" sum="d41d8cd98f00b204e9800998ecf8427e" expanded="true">
</theory>
<theory name="Bit_int64_of_Bit_uint16" sum="d41d8cd98f00b204e9800998ecf8427e" expanded="true">
</theory>
<theory name="Int8_of_Uint16" sum="d41d8cd98f00b204e9800998ecf8427e" expanded="true">
</theory>
<theory name="Bit_int8_of_Bit_uint16" sum="d41d8cd98f00b204e9800998ecf8427e" expanded="true">
</theory>
<theory name="Int16_of_Uint32" sum="d41d8cd98f00b204e9800998ecf8427e" expanded="true">
</theory>
<theory name="Bit_int16_of_Bit_uint32" sum="d41d8cd98f00b204e9800998ecf8427e" expanded="true">
</theory>
<theory name="Int32_of_Uint32" sum="d41d8cd98f00b204e9800998ecf8427e" expanded="true">
</theory>
<theory name="Bit_int32_of_Bit_uint32" sum="d41d8cd98f00b204e9800998ecf8427e" expanded="true">
</theory>
<theory name="Int64_of_Uint32" sum="d41d8cd98f00b204e9800998ecf8427e" expanded="true">
</theory>
<theory name="Bit_int64_of_Bit_uint32" sum="d41d8cd98f00b204e9800998ecf8427e" expanded="true">
</theory>
<theory name="Int8_of_Uint32" sum="d41d8cd98f00b204e9800998ecf8427e" expanded="true">
</theory>
<theory name="Bit_int8_of_Bit_uint32" sum="d41d8cd98f00b204e9800998ecf8427e" expanded="true">
</theory>
<theory name="Uint16_of_Uint32" sum="d41d8cd98f00b204e9800998ecf8427e" expanded="true">
</theory>
<theory name="Bit_uint16_of_Bit_uint32" sum="d41d8cd98f00b204e9800998ecf8427e" expanded="true">
</theory>
<theory name="Int16_of_Uint64" sum="d41d8cd98f00b204e9800998ecf8427e" expanded="true">
</theory>
<theory name="Bit_int16_of_Bit_uint64" sum="d41d8cd98f00b204e9800998ecf8427e" expanded="true">
</theory>
<theory name="Int32_of_Uint64" sum="d41d8cd98f00b204e9800998ecf8427e" expanded="true">
</theory>
<theory name="Bit_int32_of_Bit_uint64" sum="d41d8cd98f00b204e9800998ecf8427e" expanded="true">
</theory>
<theory name="Int64_of_Uint64" sum="d41d8cd98f00b204e9800998ecf8427e" expanded="true">
</theory>
<theory name="Bit_int64_of_Bit_uint64" sum="d41d8cd98f00b204e9800998ecf8427e" expanded="true">
</theory>
<theory name="Int8_of_Uint64" sum="d41d8cd98f00b204e9800998ecf8427e" expanded="true">
</theory>
<theory name="Bit_int8_of_Bit_uint64" sum="d41d8cd98f00b204e9800998ecf8427e" expanded="true">
</theory>
<theory name="Uint16_of_Uint64" sum="d41d8cd98f00b204e9800998ecf8427e" expanded="true">
</theory>
<theory name="Bit_uint16_of_Bit_uint64" sum="d41d8cd98f00b204e9800998ecf8427e" expanded="true">
</theory>
<theory name="Uint32_of_Uint64" sum="d41d8cd98f00b204e9800998ecf8427e" expanded="true">
</theory>
<theory name="Bit_uint32_of_Bit_uint64" sum="d41d8cd98f00b204e9800998ecf8427e" expanded="true">
</theory>
<theory name="Int16_of_Uint8" sum="d41d8cd98f00b204e9800998ecf8427e" expanded="true">
</theory>
<theory name="Bit_int16_of_Bit_uint8" sum="d41d8cd98f00b204e9800998ecf8427e" expanded="true">
</theory>
<theory name="Int32_of_Uint8" sum="d41d8cd98f00b204e9800998ecf8427e" expanded="true">
</theory>
<theory name="Bit_int32_of_Bit_uint8" sum="d41d8cd98f00b204e9800998ecf8427e" expanded="true">
</theory>
<theory name="Int64_of_Uint8" sum="d41d8cd98f00b204e9800998ecf8427e" expanded="true">
</theory>
<theory name="Bit_int64_of_Bit_uint8" sum="d41d8cd98f00b204e9800998ecf8427e" expanded="true">
</theory>
<theory name="Int8_of_Uint8" sum="d41d8cd98f00b204e9800998ecf8427e" expanded="true">
</theory>
<theory name="Bit_int8_of_Bit_uint8" sum="d41d8cd98f00b204e9800998ecf8427e" expanded="true">
</theory>
<theory name="Uint16_of_Uint8" sum="d41d8cd98f00b204e9800998ecf8427e" expanded="true">
</theory>
<theory name="Bit_uint16_of_Bit_uint8" sum="d41d8cd98f00b204e9800998ecf8427e" expanded="true">
</theory>
<theory name="Uint32_of_Uint8" sum="d41d8cd98f00b204e9800998ecf8427e" expanded="true">
</theory>
<theory name="Bit_uint32_of_Bit_uint8" sum="d41d8cd98f00b204e9800998ecf8427e" expanded="true">
</theory>
<theory name="Uint64_of_Uint8" sum="d41d8cd98f00b204e9800998ecf8427e" expanded="true">
</theory>
<theory name="Bit_uint64_of_Bit_uint8" sum="d41d8cd98f00b204e9800998ecf8427e" expanded="true">
</theory>
<theory name="Unsafe_uint8" sum="d41d8cd98f00b204e9800998ecf8427e" expanded="true">
</theory>
<theory name="Safe_uint8" sum="d41d8cd98f00b204e9800998ecf8427e" expanded="true">
</theory>
<theory name="Unsafe_bit_uint8" sum="d41d8cd98f00b204e9800998ecf8427e" expanded="true">
</theory>
<theory name="Safe_bit_uint8" sum="d41d8cd98f00b204e9800998ecf8427e" expanded="true">
</theory>
<theory name="Unsafe_uint64" sum="d41d8cd98f00b204e9800998ecf8427e" expanded="true">
</theory>
<theory name="Safe_uint64" sum="d41d8cd98f00b204e9800998ecf8427e" expanded="true">
</theory>
<theory name="Unsafe_bit_uint64" sum="d41d8cd98f00b204e9800998ecf8427e" expanded="true">
</theory>
<theory name="Safe_bit_uint64" sum="d41d8cd98f00b204e9800998ecf8427e" expanded="true">
</theory>
<theory name="Unsafe_uint32" sum="d41d8cd98f00b204e9800998ecf8427e" expanded="true">
</theory>
<theory name="Safe_uint32" sum="d41d8cd98f00b204e9800998ecf8427e" expanded="true">
</theory>
<theory name="Unsafe_bit_uint32" sum="d41d8cd98f00b204e9800998ecf8427e" expanded="true">
</theory>
<theory name="Safe_bit_uint32" sum="d41d8cd98f00b204e9800998ecf8427e" expanded="true">
</theory>
<theory name="Unsafe_uint16" sum="d41d8cd98f00b204e9800998ecf8427e" expanded="true">
</theory>
<theory name="Safe_uint16" sum="d41d8cd98f00b204e9800998ecf8427e" expanded="true">
</theory>
<theory name="Unsafe_bit_uint16" sum="d41d8cd98f00b204e9800998ecf8427e" expanded="true">
</theory>
<theory name="Safe_bit_uint16" sum="d41d8cd98f00b204e9800998ecf8427e" expanded="true">
</theory>
<theory name="Unsafe_int8" sum="d41d8cd98f00b204e9800998ecf8427e" expanded="true">
</theory>
<theory name="Safe_int8" sum="d41d8cd98f00b204e9800998ecf8427e" expanded="true">
</theory>
<theory name="Unsafe_bit_int8" sum="d41d8cd98f00b204e9800998ecf8427e" expanded="true">
</theory>
<theory name="Safe_bit_int8" sum="d41d8cd98f00b204e9800998ecf8427e" expanded="true">
</theory>
<theory name="Unsafe_int64" sum="d41d8cd98f00b204e9800998ecf8427e" expanded="true">
</theory>
<theory name="Safe_int64" sum="d41d8cd98f00b204e9800998ecf8427e" expanded="true">
</theory>
<theory name="Unsafe_bit_int64" sum="d41d8cd98f00b204e9800998ecf8427e" expanded="true">
</theory>
<theory name="Safe_bit_int64" sum="d41d8cd98f00b204e9800998ecf8427e" expanded="true">
</theory>
<theory name="Unsafe_int32" sum="d41d8cd98f00b204e9800998ecf8427e" expanded="true">
</theory>
<theory name="Safe_int32" sum="d41d8cd98f00b204e9800998ecf8427e" expanded="true">
</theory>
<theory name="Unsafe_bit_int32" sum="d41d8cd98f00b204e9800998ecf8427e" expanded="true">
</theory>
<theory name="Safe_bit_int32" sum="d41d8cd98f00b204e9800998ecf8427e" expanded="true">
</theory>
<theory name="Unsafe_int16" sum="d41d8cd98f00b204e9800998ecf8427e" expanded="true">
</theory>
<theory name="Safe_int16" sum="d41d8cd98f00b204e9800998ecf8427e" expanded="true">
</theory>
<theory name="Unsafe_bit_int16" sum="d41d8cd98f00b204e9800998ecf8427e" expanded="true">
</theory>
<theory name="Safe_bit_int16" sum="d41d8cd98f00b204e9800998ecf8427e" expanded="true">
</theory>
<theory name="Globals_simple" sum="d41d8cd98f00b204e9800998ecf8427e" expanded="true">
</theory>
<theory name="Root_voidP" sum="d41d8cd98f00b204e9800998ecf8427e" expanded="true">
</theory>
<theory name="Root_voidP_safe" sum="d41d8cd98f00b204e9800998ecf8427e" expanded="true">
</theory>
<theory name="Root_voidP_unsafe" sum="d41d8cd98f00b204e9800998ecf8427e" expanded="true">
</theory>
<theory name="Root_unsigned_charP_safe" sum="d41d8cd98f00b204e9800998ecf8427e" expanded="true">
</theory>
<theory name="Root_unsigned_charP_unsafe" sum="d41d8cd98f00b204e9800998ecf8427e" expanded="true">
</theory>
<theory name="Root_char_xP_safe" sum="d41d8cd98f00b204e9800998ecf8427e" expanded="true">
</theory>
<theory name="Root_char_xP_unsafe" sum="d41d8cd98f00b204e9800998ecf8427e" expanded="true">
</theory>
<theory name="Axiomatic_Strlen" sum="caf75b263ca2ba4c120ecdd3aad60eb7" expanded="true">
 <goal name="Valid_str_shift1" expl="Lemma valid_str_shift1" expanded="true">
 </goal>
 <goal name="Valid_str_strend" expl="Lemma valid_str_strend" expanded="true">
 </goal>
 <goal name="Strlen_before_null" expl="Lemma strlen_before_null" expanded="true">
 </goal>
 <goal name="Strlen_at_null" expl="Lemma strlen_at_null" expanded="true">
 </goal>
 <goal name="Strlen_shift" expl="Lemma strlen_shift" expanded="true">
 </goal>
 <goal name="Strlen_shift_ex" expl="Lemma strlen_shift_ex" expanded="true">
 </goal>
 <goal name="Strlen_shift1" expl="Lemma strlen_shift1" expanded="true">
 </goal>
 <goal name="Strlen_pointers" expl="Lemma strlen_pointers" expanded="true">
 </goal>
 <goal name="Strlen_main" expl="Lemma strlen_main" expanded="true">
 </goal>
 <goal name="Valid_str_shiftn" expl="Lemma valid_str_shiftn" expanded="true">
 </goal>
</theory>
<theory name="Axiomatic_StrSpn" sum="43c1ccf43325bccee2718289a2e59f29" expanded="true">
 <goal name="In_array_shift1" expl="Lemma in_array_shift1" expanded="true">
 </goal>
 <goal name="In_array_true" expl="Lemma in_array_true" expanded="true">
 </goal>
 <goal name="In_array_false" expl="Lemma in_array_false" expanded="true">
 </goal>
 <goal name="Strspn_strend" expl="Lemma strspn_strend" expanded="true">
 </goal>
 <goal name="Strspn_empty_accept" expl="Lemma strspn_empty_accept" expanded="true">
 </goal>
 <goal name="Strspn_range" expl="Lemma strspn_range" expanded="true">
 </goal>
 <goal name="Strspn_shift1" expl="Lemma strspn_shift1" expanded="true">
 </goal>
 <goal name="Strspn_stop_not_in_accept" expl="Lemma strspn_stop_not_in_accept" expanded="true">
 </goal>
</theory>
<theory name="Axiomatic_StrPBrk" sum="970a286b4a03102998b463c3ce19bda8" expanded="true">
 <goal name="Strpbrk_strend" expl="Lemma strpbrk_strend" expanded="true">
 </goal>
 <goal name="Strpbrk_empty_ct" expl="Lemma strpbrk_empty_ct" expanded="true">
 </goal>
 <goal name="Strpbrk_range" expl="Lemma strpbrk_range" expanded="true">
 </goal>
 <goal name="Strpbrk_shift1" expl="Lemma strpbrk_shift1" expanded="true">
 </goal>
 <goal name="Strpbrk_stop_in_ct" expl="Lemma strpbrk_stop_in_ct" expanded="true">
 </goal>
</theory>
<theory name="Root_char_xP" sum="d41d8cd98f00b204e9800998ecf8427e" expanded="true">
</theory>
<theory name="Exceptions" sum="d41d8cd98f00b204e9800998ecf8427e" expanded="true">
</theory>
<theory name="Function_strpbrk_0_safe" sum="d41d8cd98f00b204e9800998ecf8427e" expanded="true">
</theory>
<theory name="Safe_int8_of_Safe_int32" sum="d41d8cd98f00b204e9800998ecf8427e" expanded="true">
</theory>
<theory name="Function_strpbrk_0" sum="d41d8cd98f00b204e9800998ecf8427e" expanded="true">
</theory>
<theory name="Unsafe_int8_of_Unsafe_int32" sum="d41d8cd98f00b204e9800998ecf8427e" expanded="true">
</theory>
<theory name="Logic_type_padding" sum="d41d8cd98f00b204e9800998ecf8427e" expanded="true">
</theory>
<theory name="Struct_voidP" sum="d41d8cd98f00b204e9800998ecf8427e" expanded="true">
</theory>
<theory name="Struct_charP" sum="d41d8cd98f00b204e9800998ecf8427e" expanded="true">
</theory>
<theory name="Struct_charP_unsafe" sum="d41d8cd98f00b204e9800998ecf8427e" expanded="true">
</theory>
<theory name="Struct_charP_safe" sum="d41d8cd98f00b204e9800998ecf8427e" expanded="true">
</theory>
<theory name="Struct_char_xP" sum="d41d8cd98f00b204e9800998ecf8427e" expanded="true">
</theory>
<theory name="Struct_char_xP_unsafe" sum="d41d8cd98f00b204e9800998ecf8427e" expanded="true">
</theory>
<theory name="Struct_char_xP_safe" sum="d41d8cd98f00b204e9800998ecf8427e" expanded="true">
</theory>
<theory name="Root_unsigned_charP" sum="d41d8cd98f00b204e9800998ecf8427e" expanded="true">
</theory>
<theory name="Struct_unsigned_charP" sum="d41d8cd98f00b204e9800998ecf8427e" expanded="true">
</theory>
<theory name="Struct_unsigned_charP_unsafe" sum="d41d8cd98f00b204e9800998ecf8427e" expanded="true">
</theory>
<theory name="Struct_unsigned_charP_safe" sum="d41d8cd98f00b204e9800998ecf8427e" expanded="true">
</theory>
<theory name="Struct_voidP_unsafe" sum="d41d8cd98f00b204e9800998ecf8427e" expanded="true">
</theory>
<theory name="Struct_voidP_safe" sum="d41d8cd98f00b204e9800998ecf8427e" expanded="true">
</theory>
<theory name="Safe_bit_uint64_of_Safe_bit_uint8" sum="d41d8cd98f00b204e9800998ecf8427e" expanded="true">
</theory>
<theory name="Unsafe_bit_uint64_of_Unsafe_bit_uint8" sum="d41d8cd98f00b204e9800998ecf8427e" expanded="true">
</theory>
<theory name="Safe_uint64_of_Safe_uint8" sum="d41d8cd98f00b204e9800998ecf8427e" expanded="true">
</theory>
<theory name="Unsafe_uint64_of_Unsafe_uint8" sum="d41d8cd98f00b204e9800998ecf8427e" expanded="true">
</theory>
<theory name="Safe_bit_uint32_of_Safe_bit_uint8" sum="d41d8cd98f00b204e9800998ecf8427e" expanded="true">
</theory>
<theory name="Unsafe_bit_uint32_of_Unsafe_bit_uint8" sum="d41d8cd98f00b204e9800998ecf8427e" expanded="true">
</theory>
<theory name="Safe_uint32_of_Safe_uint8" sum="d41d8cd98f00b204e9800998ecf8427e" expanded="true">
</theory>
<theory name="Unsafe_uint32_of_Unsafe_uint8" sum="d41d8cd98f00b204e9800998ecf8427e" expanded="true">
</theory>
<theory name="Safe_bit_uint16_of_Safe_bit_uint8" sum="d41d8cd98f00b204e9800998ecf8427e" expanded="true">
</theory>
<theory name="Unsafe_bit_uint16_of_Unsafe_bit_uint8" sum="d41d8cd98f00b204e9800998ecf8427e" expanded="true">
</theory>
<theory name="Safe_uint16_of_Safe_uint8" sum="d41d8cd98f00b204e9800998ecf8427e" expanded="true">
</theory>
<theory name="Unsafe_uint16_of_Unsafe_uint8" sum="d41d8cd98f00b204e9800998ecf8427e" expanded="true">
</theory>
<theory name="Safe_bit_int8_of_Safe_bit_uint8" sum="d41d8cd98f00b204e9800998ecf8427e" expanded="true">
</theory>
<theory name="Unsafe_bit_int8_of_Unsafe_bit_uint8" sum="d41d8cd98f00b204e9800998ecf8427e" expanded="true">
</theory>
<theory name="Safe_int8_of_Safe_uint8" sum="d41d8cd98f00b204e9800998ecf8427e" expanded="true">
</theory>
<theory name="Unsafe_int8_of_Unsafe_uint8" sum="d41d8cd98f00b204e9800998ecf8427e" expanded="true">
</theory>
<theory name="Safe_bit_int64_of_Safe_bit_uint8" sum="d41d8cd98f00b204e9800998ecf8427e" expanded="true">
</theory>
<theory name="Unsafe_bit_int64_of_Unsafe_bit_uint8" sum="d41d8cd98f00b204e9800998ecf8427e" expanded="true">
</theory>
<theory name="Safe_int64_of_Safe_uint8" sum="d41d8cd98f00b204e9800998ecf8427e" expanded="true">
</theory>
<theory name="Unsafe_int64_of_Unsafe_uint8" sum="d41d8cd98f00b204e9800998ecf8427e" expanded="true">
</theory>
<theory name="Safe_bit_int32_of_Safe_bit_uint8" sum="d41d8cd98f00b204e9800998ecf8427e" expanded="true">
</theory>
<theory name="Unsafe_bit_int32_of_Unsafe_bit_uint8" sum="d41d8cd98f00b204e9800998ecf8427e" expanded="true">
</theory>
<theory name="Safe_int32_of_Safe_uint8" sum="d41d8cd98f00b204e9800998ecf8427e" expanded="true">
</theory>
<theory name="Unsafe_int32_of_Unsafe_uint8" sum="d41d8cd98f00b204e9800998ecf8427e" expanded="true">
</theory>
<theory name="Safe_bit_int16_of_Safe_bit_uint8" sum="d41d8cd98f00b204e9800998ecf8427e" expanded="true">
</theory>
<theory name="Unsafe_bit_int16_of_Unsafe_bit_uint8" sum="d41d8cd98f00b204e9800998ecf8427e" expanded="true">
</theory>
<theory name="Safe_int16_of_Safe_uint8" sum="d41d8cd98f00b204e9800998ecf8427e" expanded="true">
</theory>
<theory name="Unsafe_int16_of_Unsafe_uint8" sum="d41d8cd98f00b204e9800998ecf8427e" expanded="true">
</theory>
<theory name="Safe_bit_uint32_of_Safe_bit_uint64" sum="d41d8cd98f00b204e9800998ecf8427e" expanded="true">
</theory>
<theory name="Unsafe_bit_uint32_of_Unsafe_bit_uint64" sum="d41d8cd98f00b204e9800998ecf8427e" expanded="true">
</theory>
<theory name="Safe_uint32_of_Safe_uint64" sum="d41d8cd98f00b204e9800998ecf8427e" expanded="true">
</theory>
<theory name="Unsafe_uint32_of_Unsafe_uint64" sum="d41d8cd98f00b204e9800998ecf8427e" expanded="true">
</theory>
<theory name="Safe_bit_uint16_of_Safe_bit_uint64" sum="d41d8cd98f00b204e9800998ecf8427e" expanded="true">
</theory>
<theory name="Unsafe_bit_uint16_of_Unsafe_bit_uint64" sum="d41d8cd98f00b204e9800998ecf8427e" expanded="true">
</theory>
<theory name="Safe_uint16_of_Safe_uint64" sum="d41d8cd98f00b204e9800998ecf8427e" expanded="true">
</theory>
<theory name="Unsafe_uint16_of_Unsafe_uint64" sum="d41d8cd98f00b204e9800998ecf8427e" expanded="true">
</theory>
<theory name="Safe_bit_int8_of_Safe_bit_uint64" sum="d41d8cd98f00b204e9800998ecf8427e" expanded="true">
</theory>
<theory name="Unsafe_bit_int8_of_Unsafe_bit_uint64" sum="d41d8cd98f00b204e9800998ecf8427e" expanded="true">
</theory>
<theory name="Safe_int8_of_Safe_uint64" sum="d41d8cd98f00b204e9800998ecf8427e" expanded="true">
</theory>
<theory name="Unsafe_int8_of_Unsafe_uint64" sum="d41d8cd98f00b204e9800998ecf8427e" expanded="true">
</theory>
<theory name="Safe_bit_int64_of_Safe_bit_uint64" sum="d41d8cd98f00b204e9800998ecf8427e" expanded="true">
</theory>
<theory name="Unsafe_bit_int64_of_Unsafe_bit_uint64" sum="d41d8cd98f00b204e9800998ecf8427e" expanded="true">
</theory>
<theory name="Safe_int64_of_Safe_uint64" sum="d41d8cd98f00b204e9800998ecf8427e" expanded="true">
</theory>
<theory name="Unsafe_int64_of_Unsafe_uint64" sum="d41d8cd98f00b204e9800998ecf8427e" expanded="true">
</theory>
<theory name="Safe_bit_int32_of_Safe_bit_uint64" sum="d41d8cd98f00b204e9800998ecf8427e" expanded="true">
</theory>
<theory name="Unsafe_bit_int32_of_Unsafe_bit_uint64" sum="d41d8cd98f00b204e9800998ecf8427e" expanded="true">
</theory>
<theory name="Safe_int32_of_Safe_uint64" sum="d41d8cd98f00b204e9800998ecf8427e" expanded="true">
</theory>
<theory name="Unsafe_int32_of_Unsafe_uint64" sum="d41d8cd98f00b204e9800998ecf8427e" expanded="true">
</theory>
<theory name="Safe_bit_int16_of_Safe_bit_uint64" sum="d41d8cd98f00b204e9800998ecf8427e" expanded="true">
</theory>
<theory name="Unsafe_bit_int16_of_Unsafe_bit_uint64" sum="d41d8cd98f00b204e9800998ecf8427e" expanded="true">
</theory>
<theory name="Safe_int16_of_Safe_uint64" sum="d41d8cd98f00b204e9800998ecf8427e" expanded="true">
</theory>
<theory name="Unsafe_int16_of_Unsafe_uint64" sum="d41d8cd98f00b204e9800998ecf8427e" expanded="true">
</theory>
<theory name="Safe_bit_uint16_of_Safe_bit_uint32" sum="d41d8cd98f00b204e9800998ecf8427e" expanded="true">
</theory>
<theory name="Unsafe_bit_uint16_of_Unsafe_bit_uint32" sum="d41d8cd98f00b204e9800998ecf8427e" expanded="true">
</theory>
<theory name="Safe_uint16_of_Safe_uint32" sum="d41d8cd98f00b204e9800998ecf8427e" expanded="true">
</theory>
<theory name="Unsafe_uint16_of_Unsafe_uint32" sum="d41d8cd98f00b204e9800998ecf8427e" expanded="true">
</theory>
<theory name="Safe_bit_int8_of_Safe_bit_uint32" sum="d41d8cd98f00b204e9800998ecf8427e" expanded="true">
</theory>
<theory name="Unsafe_bit_int8_of_Unsafe_bit_uint32" sum="d41d8cd98f00b204e9800998ecf8427e" expanded="true">
</theory>
<theory name="Safe_int8_of_Safe_uint32" sum="d41d8cd98f00b204e9800998ecf8427e" expanded="true">
</theory>
<theory name="Unsafe_int8_of_Unsafe_uint32" sum="d41d8cd98f00b204e9800998ecf8427e" expanded="true">
</theory>
<theory name="Safe_bit_int64_of_Safe_bit_uint32" sum="d41d8cd98f00b204e9800998ecf8427e" expanded="true">
</theory>
<theory name="Unsafe_bit_int64_of_Unsafe_bit_uint32" sum="d41d8cd98f00b204e9800998ecf8427e" expanded="true">
</theory>
<theory name="Safe_int64_of_Safe_uint32" sum="d41d8cd98f00b204e9800998ecf8427e" expanded="true">
</theory>
<theory name="Unsafe_int64_of_Unsafe_uint32" sum="d41d8cd98f00b204e9800998ecf8427e" expanded="true">
</theory>
<theory name="Safe_bit_int32_of_Safe_bit_uint32" sum="d41d8cd98f00b204e9800998ecf8427e" expanded="true">
</theory>
<theory name="Unsafe_bit_int32_of_Unsafe_bit_uint32" sum="d41d8cd98f00b204e9800998ecf8427e" expanded="true">
</theory>
<theory name="Safe_int32_of_Safe_uint32" sum="d41d8cd98f00b204e9800998ecf8427e" expanded="true">
</theory>
<theory name="Unsafe_int32_of_Unsafe_uint32" sum="d41d8cd98f00b204e9800998ecf8427e" expanded="true">
</theory>
<theory name="Safe_bit_int16_of_Safe_bit_uint32" sum="d41d8cd98f00b204e9800998ecf8427e" expanded="true">
</theory>
<theory name="Unsafe_bit_int16_of_Unsafe_bit_uint32" sum="d41d8cd98f00b204e9800998ecf8427e" expanded="true">
</theory>
<theory name="Safe_int16_of_Safe_uint32" sum="d41d8cd98f00b204e9800998ecf8427e" expanded="true">
</theory>
<theory name="Unsafe_int16_of_Unsafe_uint32" sum="d41d8cd98f00b204e9800998ecf8427e" expanded="true">
</theory>
<theory name="Safe_bit_int8_of_Safe_bit_uint16" sum="d41d8cd98f00b204e9800998ecf8427e" expanded="true">
</theory>
<theory name="Unsafe_bit_int8_of_Unsafe_bit_uint16" sum="d41d8cd98f00b204e9800998ecf8427e" expanded="true">
</theory>
<theory name="Safe_int8_of_Safe_uint16" sum="d41d8cd98f00b204e9800998ecf8427e" expanded="true">
</theory>
<theory name="Unsafe_int8_of_Unsafe_uint16" sum="d41d8cd98f00b204e9800998ecf8427e" expanded="true">
</theory>
<theory name="Safe_bit_int64_of_Safe_bit_uint16" sum="d41d8cd98f00b204e9800998ecf8427e" expanded="true">
</theory>
<theory name="Unsafe_bit_int64_of_Unsafe_bit_uint16" sum="d41d8cd98f00b204e9800998ecf8427e" expanded="true">
</theory>
<theory name="Safe_int64_of_Safe_uint16" sum="d41d8cd98f00b204e9800998ecf8427e" expanded="true">
</theory>
<theory name="Unsafe_int64_of_Unsafe_uint16" sum="d41d8cd98f00b204e9800998ecf8427e" expanded="true">
</theory>
<theory name="Safe_bit_int32_of_Safe_bit_uint16" sum="d41d8cd98f00b204e9800998ecf8427e" expanded="true">
</theory>
<theory name="Unsafe_bit_int32_of_Unsafe_bit_uint16" sum="d41d8cd98f00b204e9800998ecf8427e" expanded="true">
</theory>
<theory name="Safe_int32_of_Safe_uint16" sum="d41d8cd98f00b204e9800998ecf8427e" expanded="true">
</theory>
<theory name="Unsafe_int32_of_Unsafe_uint16" sum="d41d8cd98f00b204e9800998ecf8427e" expanded="true">
</theory>
<theory name="Safe_bit_int16_of_Safe_bit_uint16" sum="d41d8cd98f00b204e9800998ecf8427e" expanded="true">
</theory>
<theory name="Unsafe_bit_int16_of_Unsafe_bit_uint16" sum="d41d8cd98f00b204e9800998ecf8427e" expanded="true">
</theory>
<theory name="Safe_int16_of_Safe_uint16" sum="d41d8cd98f00b204e9800998ecf8427e" expanded="true">
</theory>
<theory name="Unsafe_int16_of_Unsafe_uint16" sum="d41d8cd98f00b204e9800998ecf8427e" expanded="true">
</theory>
<theory name="Safe_bit_int64_of_Safe_bit_int8" sum="d41d8cd98f00b204e9800998ecf8427e" expanded="true">
</theory>
<theory name="Unsafe_bit_int64_of_Unsafe_bit_int8" sum="d41d8cd98f00b204e9800998ecf8427e" expanded="true">
</theory>
<theory name="Safe_int64_of_Safe_int8" sum="d41d8cd98f00b204e9800998ecf8427e" expanded="true">
</theory>
<theory name="Unsafe_int64_of_Unsafe_int8" sum="d41d8cd98f00b204e9800998ecf8427e" expanded="true">
</theory>
<theory name="Safe_bit_int32_of_Safe_bit_int8" sum="d41d8cd98f00b204e9800998ecf8427e" expanded="true">
</theory>
<theory name="Unsafe_bit_int32_of_Unsafe_bit_int8" sum="d41d8cd98f00b204e9800998ecf8427e" expanded="true">
</theory>
<theory name="Safe_int32_of_Safe_int8" sum="d41d8cd98f00b204e9800998ecf8427e" expanded="true">
</theory>
<theory name="Unsafe_int32_of_Unsafe_int8" sum="d41d8cd98f00b204e9800998ecf8427e" expanded="true">
</theory>
<theory name="Safe_bit_int16_of_Safe_bit_int8" sum="d41d8cd98f00b204e9800998ecf8427e" expanded="true">
</theory>
<theory name="Unsafe_bit_int16_of_Unsafe_bit_int8" sum="d41d8cd98f00b204e9800998ecf8427e" expanded="true">
</theory>
<theory name="Safe_int16_of_Safe_int8" sum="d41d8cd98f00b204e9800998ecf8427e" expanded="true">
</theory>
<theory name="Unsafe_int16_of_Unsafe_int8" sum="d41d8cd98f00b204e9800998ecf8427e" expanded="true">
</theory>
<theory name="Safe_bit_int32_of_Safe_bit_int64" sum="d41d8cd98f00b204e9800998ecf8427e" expanded="true">
</theory>
<theory name="Unsafe_bit_int32_of_Unsafe_bit_int64" sum="d41d8cd98f00b204e9800998ecf8427e" expanded="true">
</theory>
<theory name="Safe_int32_of_Safe_int64" sum="d41d8cd98f00b204e9800998ecf8427e" expanded="true">
</theory>
<theory name="Unsafe_int32_of_Unsafe_int64" sum="d41d8cd98f00b204e9800998ecf8427e" expanded="true">
</theory>
<theory name="Safe_bit_int16_of_Safe_bit_int64" sum="d41d8cd98f00b204e9800998ecf8427e" expanded="true">
</theory>
<theory name="Unsafe_bit_int16_of_Unsafe_bit_int64" sum="d41d8cd98f00b204e9800998ecf8427e" expanded="true">
</theory>
<theory name="Safe_int16_of_Safe_int64" sum="d41d8cd98f00b204e9800998ecf8427e" expanded="true">
</theory>
<theory name="Unsafe_int16_of_Unsafe_int64" sum="d41d8cd98f00b204e9800998ecf8427e" expanded="true">
</theory>
<theory name="Safe_bit_int16_of_Safe_bit_int32" sum="d41d8cd98f00b204e9800998ecf8427e" expanded="true">
</theory>
<theory name="Unsafe_bit_int16_of_Unsafe_bit_int32" sum="d41d8cd98f00b204e9800998ecf8427e" expanded="true">
</theory>
<theory name="Safe_int16_of_Safe_int32" sum="d41d8cd98f00b204e9800998ecf8427e" expanded="true">
</theory>
<theory name="Unsafe_int16_of_Unsafe_int32" sum="d41d8cd98f00b204e9800998ecf8427e" expanded="true">
</theory>
<theory name="Safe_bit_uint8_of_Safe_bit_uint64" sum="d41d8cd98f00b204e9800998ecf8427e" expanded="true">
</theory>
<theory name="Unsafe_bit_uint8_of_Unsafe_bit_uint64" sum="d41d8cd98f00b204e9800998ecf8427e" expanded="true">
</theory>
<theory name="Safe_uint8_of_Safe_uint64" sum="d41d8cd98f00b204e9800998ecf8427e" expanded="true">
</theory>
<theory name="Unsafe_uint8_of_Unsafe_uint64" sum="d41d8cd98f00b204e9800998ecf8427e" expanded="true">
</theory>
<theory name="Safe_bit_uint8_of_Safe_bit_uint32" sum="d41d8cd98f00b204e9800998ecf8427e" expanded="true">
</theory>
<theory name="Unsafe_bit_uint8_of_Unsafe_bit_uint32" sum="d41d8cd98f00b204e9800998ecf8427e" expanded="true">
</theory>
<theory name="Safe_uint8_of_Safe_uint32" sum="d41d8cd98f00b204e9800998ecf8427e" expanded="true">
</theory>
<theory name="Unsafe_uint8_of_Unsafe_uint32" sum="d41d8cd98f00b204e9800998ecf8427e" expanded="true">
</theory>
<theory name="Safe_bit_uint8_of_Safe_bit_uint16" sum="d41d8cd98f00b204e9800998ecf8427e" expanded="true">
</theory>
<theory name="Unsafe_bit_uint8_of_Unsafe_bit_uint16" sum="d41d8cd98f00b204e9800998ecf8427e" expanded="true">
</theory>
<theory name="Safe_uint8_of_Safe_uint16" sum="d41d8cd98f00b204e9800998ecf8427e" expanded="true">
</theory>
<theory name="Unsafe_uint8_of_Unsafe_uint16" sum="d41d8cd98f00b204e9800998ecf8427e" expanded="true">
</theory>
<theory name="Safe_bit_uint8_of_Safe_bit_int8" sum="d41d8cd98f00b204e9800998ecf8427e" expanded="true">
</theory>
<theory name="Unsafe_bit_uint8_of_Unsafe_bit_int8" sum="d41d8cd98f00b204e9800998ecf8427e" expanded="true">
</theory>
<theory name="Safe_uint8_of_Safe_int8" sum="d41d8cd98f00b204e9800998ecf8427e" expanded="true">
</theory>
<theory name="Unsafe_uint8_of_Unsafe_int8" sum="d41d8cd98f00b204e9800998ecf8427e" expanded="true">
</theory>
<theory name="Safe_bit_uint8_of_Safe_bit_int64" sum="d41d8cd98f00b204e9800998ecf8427e" expanded="true">
</theory>
<theory name="Unsafe_bit_uint8_of_Unsafe_bit_int64" sum="d41d8cd98f00b204e9800998ecf8427e" expanded="true">
</theory>
<theory name="Safe_uint8_of_Safe_int64" sum="d41d8cd98f00b204e9800998ecf8427e" expanded="true">
</theory>
<theory name="Unsafe_uint8_of_Unsafe_int64" sum="d41d8cd98f00b204e9800998ecf8427e" expanded="true">
</theory>
<theory name="Safe_bit_uint8_of_Safe_bit_int32" sum="d41d8cd98f00b204e9800998ecf8427e" expanded="true">
</theory>
<theory name="Unsafe_bit_uint8_of_Unsafe_bit_int32" sum="d41d8cd98f00b204e9800998ecf8427e" expanded="true">
</theory>
<theory name="Safe_uint8_of_Safe_int32" sum="d41d8cd98f00b204e9800998ecf8427e" expanded="true">
</theory>
<theory name="Unsafe_uint8_of_Unsafe_int32" sum="d41d8cd98f00b204e9800998ecf8427e" expanded="true">
</theory>
<theory name="Safe_bit_uint8_of_Safe_bit_int16" sum="d41d8cd98f00b204e9800998ecf8427e" expanded="true">
</theory>
<theory name="Unsafe_bit_uint8_of_Unsafe_bit_int16" sum="d41d8cd98f00b204e9800998ecf8427e" expanded="true">
</theory>
<theory name="Safe_uint8_of_Safe_int16" sum="d41d8cd98f00b204e9800998ecf8427e" expanded="true">
</theory>
<theory name="Unsafe_uint8_of_Unsafe_int16" sum="d41d8cd98f00b204e9800998ecf8427e" expanded="true">
</theory>
<theory name="Safe_bit_uint64_of_Safe_bit_uint32" sum="d41d8cd98f00b204e9800998ecf8427e" expanded="true">
</theory>
<theory name="Unsafe_bit_uint64_of_Unsafe_bit_uint32" sum="d41d8cd98f00b204e9800998ecf8427e" expanded="true">
</theory>
<theory name="Safe_uint64_of_Safe_uint32" sum="d41d8cd98f00b204e9800998ecf8427e" expanded="true">
</theory>
<theory name="Unsafe_uint64_of_Unsafe_uint32" sum="d41d8cd98f00b204e9800998ecf8427e" expanded="true">
</theory>
<theory name="Safe_bit_uint64_of_Safe_bit_uint16" sum="d41d8cd98f00b204e9800998ecf8427e" expanded="true">
</theory>
<theory name="Unsafe_bit_uint64_of_Unsafe_bit_uint16" sum="d41d8cd98f00b204e9800998ecf8427e" expanded="true">
</theory>
<theory name="Safe_uint64_of_Safe_uint16" sum="d41d8cd98f00b204e9800998ecf8427e" expanded="true">
</theory>
<theory name="Unsafe_uint64_of_Unsafe_uint16" sum="d41d8cd98f00b204e9800998ecf8427e" expanded="true">
</theory>
<theory name="Safe_bit_uint64_of_Safe_bit_int8" sum="d41d8cd98f00b204e9800998ecf8427e" expanded="true">
</theory>
<theory name="Unsafe_bit_uint64_of_Unsafe_bit_int8" sum="d41d8cd98f00b204e9800998ecf8427e" expanded="true">
</theory>
<theory name="Safe_uint64_of_Safe_int8" sum="d41d8cd98f00b204e9800998ecf8427e" expanded="true">
</theory>
<theory name="Unsafe_uint64_of_Unsafe_int8" sum="d41d8cd98f00b204e9800998ecf8427e" expanded="true">
</theory>
<theory name="Safe_bit_uint64_of_Safe_bit_int64" sum="d41d8cd98f00b204e9800998ecf8427e" expanded="true">
</theory>
<theory name="Unsafe_bit_uint64_of_Unsafe_bit_int64" sum="d41d8cd98f00b204e9800998ecf8427e" expanded="true">
</theory>
<theory name="Safe_uint64_of_Safe_int64" sum="d41d8cd98f00b204e9800998ecf8427e" expanded="true">
</theory>
<theory name="Unsafe_uint64_of_Unsafe_int64" sum="d41d8cd98f00b204e9800998ecf8427e" expanded="true">
</theory>
<theory name="Safe_bit_uint64_of_Safe_bit_int32" sum="d41d8cd98f00b204e9800998ecf8427e" expanded="true">
</theory>
<theory name="Unsafe_bit_uint64_of_Unsafe_bit_int32" sum="d41d8cd98f00b204e9800998ecf8427e" expanded="true">
</theory>
<theory name="Safe_uint64_of_Safe_int32" sum="d41d8cd98f00b204e9800998ecf8427e" expanded="true">
</theory>
<theory name="Unsafe_uint64_of_Unsafe_int32" sum="d41d8cd98f00b204e9800998ecf8427e" expanded="true">
</theory>
<theory name="Safe_bit_uint64_of_Safe_bit_int16" sum="d41d8cd98f00b204e9800998ecf8427e" expanded="true">
</theory>
<theory name="Unsafe_bit_uint64_of_Unsafe_bit_int16" sum="d41d8cd98f00b204e9800998ecf8427e" expanded="true">
</theory>
<theory name="Safe_uint64_of_Safe_int16" sum="d41d8cd98f00b204e9800998ecf8427e" expanded="true">
</theory>
<theory name="Unsafe_uint64_of_Unsafe_int16" sum="d41d8cd98f00b204e9800998ecf8427e" expanded="true">
</theory>
<theory name="Safe_bit_uint32_of_Safe_bit_uint16" sum="d41d8cd98f00b204e9800998ecf8427e" expanded="true">
</theory>
<theory name="Unsafe_bit_uint32_of_Unsafe_bit_uint16" sum="d41d8cd98f00b204e9800998ecf8427e" expanded="true">
</theory>
<theory name="Safe_uint32_of_Safe_uint16" sum="d41d8cd98f00b204e9800998ecf8427e" expanded="true">
</theory>
<theory name="Unsafe_uint32_of_Unsafe_uint16" sum="d41d8cd98f00b204e9800998ecf8427e" expanded="true">
</theory>
<theory name="Safe_bit_uint32_of_Safe_bit_int8" sum="d41d8cd98f00b204e9800998ecf8427e" expanded="true">
</theory>
<theory name="Unsafe_bit_uint32_of_Unsafe_bit_int8" sum="d41d8cd98f00b204e9800998ecf8427e" expanded="true">
</theory>
<theory name="Safe_uint32_of_Safe_int8" sum="d41d8cd98f00b204e9800998ecf8427e" expanded="true">
</theory>
<theory name="Unsafe_uint32_of_Unsafe_int8" sum="d41d8cd98f00b204e9800998ecf8427e" expanded="true">
</theory>
<theory name="Safe_bit_uint32_of_Safe_bit_int64" sum="d41d8cd98f00b204e9800998ecf8427e" expanded="true">
</theory>
<theory name="Unsafe_bit_uint32_of_Unsafe_bit_int64" sum="d41d8cd98f00b204e9800998ecf8427e" expanded="true">
</theory>
<theory name="Safe_uint32_of_Safe_int64" sum="d41d8cd98f00b204e9800998ecf8427e" expanded="true">
</theory>
<theory name="Unsafe_uint32_of_Unsafe_int64" sum="d41d8cd98f00b204e9800998ecf8427e" expanded="true">
</theory>
<theory name="Safe_bit_uint32_of_Safe_bit_int32" sum="d41d8cd98f00b204e9800998ecf8427e" expanded="true">
</theory>
<theory name="Unsafe_bit_uint32_of_Unsafe_bit_int32" sum="d41d8cd98f00b204e9800998ecf8427e" expanded="true">
</theory>
<theory name="Safe_uint32_of_Safe_int32" sum="d41d8cd98f00b204e9800998ecf8427e" expanded="true">
</theory>
<theory name="Unsafe_uint32_of_Unsafe_int32" sum="d41d8cd98f00b204e9800998ecf8427e" expanded="true">
</theory>
<theory name="Safe_bit_uint32_of_Safe_bit_int16" sum="d41d8cd98f00b204e9800998ecf8427e" expanded="true">
</theory>
<theory name="Unsafe_bit_uint32_of_Unsafe_bit_int16" sum="d41d8cd98f00b204e9800998ecf8427e" expanded="true">
</theory>
<theory name="Safe_uint32_of_Safe_int16" sum="d41d8cd98f00b204e9800998ecf8427e" expanded="true">
</theory>
<theory name="Unsafe_uint32_of_Unsafe_int16" sum="d41d8cd98f00b204e9800998ecf8427e" expanded="true">
</theory>
<theory name="Safe_bit_uint16_of_Safe_bit_int8" sum="d41d8cd98f00b204e9800998ecf8427e" expanded="true">
</theory>
<theory name="Unsafe_bit_uint16_of_Unsafe_bit_int8" sum="d41d8cd98f00b204e9800998ecf8427e" expanded="true">
</theory>
<theory name="Safe_uint16_of_Safe_int8" sum="d41d8cd98f00b204e9800998ecf8427e" expanded="true">
</theory>
<theory name="Unsafe_uint16_of_Unsafe_int8" sum="d41d8cd98f00b204e9800998ecf8427e" expanded="true">
</theory>
<theory name="Safe_bit_uint16_of_Safe_bit_int64" sum="d41d8cd98f00b204e9800998ecf8427e" expanded="true">
</theory>
<theory name="Unsafe_bit_uint16_of_Unsafe_bit_int64" sum="d41d8cd98f00b204e9800998ecf8427e" expanded="true">
</theory>
<theory name="Safe_uint16_of_Safe_int64" sum="d41d8cd98f00b204e9800998ecf8427e" expanded="true">
</theory>
<theory name="Unsafe_uint16_of_Unsafe_int64" sum="d41d8cd98f00b204e9800998ecf8427e" expanded="true">
</theory>
<theory name="Safe_bit_uint16_of_Safe_bit_int32" sum="d41d8cd98f00b204e9800998ecf8427e" expanded="true">
</theory>
<theory name="Unsafe_bit_uint16_of_Unsafe_bit_int32" sum="d41d8cd98f00b204e9800998ecf8427e" expanded="true">
</theory>
<theory name="Safe_uint16_of_Safe_int32" sum="d41d8cd98f00b204e9800998ecf8427e" expanded="true">
</theory>
<theory name="Unsafe_uint16_of_Unsafe_int32" sum="d41d8cd98f00b204e9800998ecf8427e" expanded="true">
</theory>
<theory name="Safe_bit_uint16_of_Safe_bit_int16" sum="d41d8cd98f00b204e9800998ecf8427e" expanded="true">
</theory>
<theory name="Unsafe_bit_uint16_of_Unsafe_bit_int16" sum="d41d8cd98f00b204e9800998ecf8427e" expanded="true">
</theory>
<theory name="Safe_uint16_of_Safe_int16" sum="d41d8cd98f00b204e9800998ecf8427e" expanded="true">
</theory>
<theory name="Unsafe_uint16_of_Unsafe_int16" sum="d41d8cd98f00b204e9800998ecf8427e" expanded="true">
</theory>
<theory name="Safe_bit_int8_of_Safe_bit_int64" sum="d41d8cd98f00b204e9800998ecf8427e" expanded="true">
</theory>
<theory name="Unsafe_bit_int8_of_Unsafe_bit_int64" sum="d41d8cd98f00b204e9800998ecf8427e" expanded="true">
</theory>
<theory name="Safe_int8_of_Safe_int64" sum="d41d8cd98f00b204e9800998ecf8427e" expanded="true">
</theory>
<theory name="Unsafe_int8_of_Unsafe_int64" sum="d41d8cd98f00b204e9800998ecf8427e" expanded="true">
</theory>
<theory name="Safe_bit_int8_of_Safe_bit_int32" sum="d41d8cd98f00b204e9800998ecf8427e" expanded="true">
</theory>
<theory name="Unsafe_bit_int8_of_Unsafe_bit_int32" sum="d41d8cd98f00b204e9800998ecf8427e" expanded="true">
</theory>
<theory name="Safe_bit_int8_of_Safe_bit_int16" sum="d41d8cd98f00b204e9800998ecf8427e" expanded="true">
</theory>
<theory name="Unsafe_bit_int8_of_Unsafe_bit_int16" sum="d41d8cd98f00b204e9800998ecf8427e" expanded="true">
</theory>
<theory name="Safe_int8_of_Safe_int16" sum="d41d8cd98f00b204e9800998ecf8427e" expanded="true">
</theory>
<theory name="Unsafe_int8_of_Unsafe_int16" sum="d41d8cd98f00b204e9800998ecf8427e" expanded="true">
</theory>
<theory name="Safe_bit_int64_of_Safe_bit_int32" sum="d41d8cd98f00b204e9800998ecf8427e" expanded="true">
</theory>
<theory name="Unsafe_bit_int64_of_Unsafe_bit_int32" sum="d41d8cd98f00b204e9800998ecf8427e" expanded="true">
</theory>
<theory name="Safe_int64_of_Safe_int32" sum="d41d8cd98f00b204e9800998ecf8427e" expanded="true">
</theory>
<theory name="Unsafe_int64_of_Unsafe_int32" sum="d41d8cd98f00b204e9800998ecf8427e" expanded="true">
</theory>
<theory name="Safe_bit_int64_of_Safe_bit_int16" sum="d41d8cd98f00b204e9800998ecf8427e" expanded="true">
</theory>
<theory name="Unsafe_bit_int64_of_Unsafe_bit_int16" sum="d41d8cd98f00b204e9800998ecf8427e" expanded="true">
</theory>
<theory name="Safe_int64_of_Safe_int16" sum="d41d8cd98f00b204e9800998ecf8427e" expanded="true">
</theory>
<theory name="Unsafe_int64_of_Unsafe_int16" sum="d41d8cd98f00b204e9800998ecf8427e" expanded="true">
</theory>
<theory name="Safe_bit_int32_of_Safe_bit_int16" sum="d41d8cd98f00b204e9800998ecf8427e" expanded="true">
</theory>
<theory name="Unsafe_bit_int32_of_Unsafe_bit_int16" sum="d41d8cd98f00b204e9800998ecf8427e" expanded="true">
</theory>
<theory name="Safe_int32_of_Safe_int16" sum="d41d8cd98f00b204e9800998ecf8427e" expanded="true">
</theory>
<theory name="Unsafe_int32_of_Unsafe_int16" sum="d41d8cd98f00b204e9800998ecf8427e" expanded="true">
</theory>
<theory name="Function_strlen_0" sum="d41d8cd98f00b204e9800998ecf8427e" expanded="true">
</theory>
<theory name="Function_strlen_0_safe" sum="d41d8cd98f00b204e9800998ecf8427e" expanded="true">
</theory>
<theory name="Function_strspn_0" sum="d41d8cd98f00b204e9800998ecf8427e" expanded="true">
</theory>
<theory name="Function_strspn_0_safe" sum="d41d8cd98f00b204e9800998ecf8427e" expanded="true">
</theory>
<theory name="Function_strsep" sum="d41d8cd98f00b204e9800998ecf8427e" expanded="true">
</theory>
<theory name="Function_strsep_safe" sum="d41d8cd98f00b204e9800998ecf8427e" expanded="true">
</theory>
</file>
</why3session>
